django_ldap_group_mapper-0.1.2.dist-info/metadata.json
django_ldap_group_mapper-0.1.2.dist-info/top_level.txt
django_ldap_group_mapper-0.1.2.dist-info/RECORD
django_ldap_group_mapper-0.1.2.dist-info/DESCRIPTION.rst
django_ldap_group_mapper-0.1.2.dist-info/METADATA
django_ldap_group_mapper-0.1.2.dist-info/WHEEL
ldap_groups/__init__.py
ldap_groups/admin.py
ldap_groups/models.py
