Metadata-Version: 2.0
Name: django-ldap-group-mapper
Version: 0.1.2
Summary: Django LDAP Group Mapper
Home-page: https://github.com/musashiXXX/django-ldap-group-mapper
Author: Charles Hamilton
Author-email: musashi@nefaria.com
License: LICENSE.txt
Download-URL: https://github.com/musashiXXX/django-ldap-group-mapper/tarball/0.1.2
Keywords: django-auth-ldap,django,ldap
Platform: UNKNOWN
Requires-Dist: django-auth-ldap (>=1.2.0)
Requires-Dist: python-ldap (>=2.0)
Requires-Dist: Django (>=1.3)
